{
  "primaryTarget": "dreamweb-cd",
  "games": [
    {
      "target": "drascula",
      "title": "Drascula: The Vampire Strikes Back (DOS/English)",
      "path": "/games/drascula",
      "engineId": "drascula",
      "gameId": "drascula",
      "platform": "pc",
      "extra": "",
      "readmeHref": "https://scummvm-games.tsilva.eu/drascula/readme.txt",
      "skipIntro": {
        "durationMinutes": 2,
        "key": "Escape",
        "pressCount": 1
      }
    },
    {
      "target": "dreamweb-cd",
      "title": "DreamWeb (CD/DOS/English)",
      "path": "/games/dreamweb",
      "engineId": "dreamweb",
      "gameId": "dreamweb",
      "platform": "pc",
      "extra": "CD",
      "readmeHref": "",
      "skipIntro": {
        "durationMinutes": 2,
        "key": "Escape",
        "pressCount": 3,
        "pressIntervalMs": 500
      }
    },
    {
      "target": "lure",
      "title": "Lure of the Temptress (VGA/DOS/English)",
      "path": "/games/lure",
      "engineId": "lure",
      "gameId": "lure",
      "platform": "pc",
      "extra": "VGA",
      "readmeHref": "https://scummvm-games.tsilva.eu/lure/README",
      "skipIntro": {
        "durationMinutes": 2,
        "key": "Escape",
        "pressCount": 1
      }
    },
    {
      "target": "nippon-amiga",
      "title": "Nippon Safes, Inc. (Multi-lingual/Amiga)",
      "path": "/games/nippon",
      "engineId": "parallaction",
      "gameId": "nippon",
      "platform": "amiga",
      "extra": "Multi-lingual",
      "readmeHref": "https://scummvm-games.tsilva.eu/nippon/readme.txt"
    },
    {
      "target": "queen",
      "title": "Flight of the Amazon Queen (CD/DOS/English)",
      "path": "/games/queen",
      "engineId": "queen",
      "gameId": "queen",
      "platform": "pc",
      "extra": "CD",
      "readmeHref": "https://scummvm-games.tsilva.eu/queen/readme.txt",
      "skipIntro": {
        "durationMinutes": 2,
        "key": "Escape",
        "pressCount": 5,
        "pressIntervalMs": 1000
      }
    },
    {
      "target": "sky",
      "title": "Beneath a Steel Sky (v0.0372 CD/DOS)",
      "path": "/games/sky",
      "engineId": "sky",
      "gameId": "sky",
      "platform": "pc",
      "extra": "v0.0372 CD",
      "readmeHref": "https://scummvm-games.tsilva.eu/sky/readme.txt",
      "skipIntro": {
        "durationMinutes": 2,
        "key": "Escape"
      }
    },
    {
      "target": "sword25",
      "title": "Broken Sword 2.5: The Return of the Templars (Latest version)",
      "path": "/games/sword25",
      "engineId": "sword25",
      "gameId": "sword25",
      "platform": "",
      "extra": "Latest version",
      "readmeHref": "https://scummvm-games.tsilva.eu/sword25/README"
    }
  ]
}
